dryad_app/__init__.py
dryad_app/dryad.config
dryad_app/dryad.nf
dryad_app/dryad.py
dryad_app/dryad_report.py
dryad_app/nextflow.config
dryad_app/rebuild_report.nf
dryad_app/__pycache__/__init__.cpython-37.pyc
dryad_app/__pycache__/dryad.cpython-37.pyc
dryad_app/assets/dryad_logo_250.png
dryad_app/assets/dryad_logo_500.png
dryad_app/configs/docker.config
dryad_app/configs/docker_containers.config
dryad_app/configs/dryad_config_template.config
dryad_app/configs/multiqc_config.yaml
dryad_app/configs/singularity.config
dryad_app/lib/nextflow
dryad_app/report/report.Rmd
dryad-2.0.2.dist-info/LICENSE
dryad-2.0.2.dist-info/METADATA
dryad-2.0.2.dist-info/WHEEL
dryad-2.0.2.dist-info/entry_points.txt
dryad-2.0.2.dist-info/top_level.txt
dryad-2.0.2.dist-info/RECORD
