Metadata-Version: 2.1
Name: dryad
Version: 2.0.2
Summary: A pipeline to construct reference free core-genome or SNP phylogenetic trees for examining prokaryote relatedness in outbreaks.
Home-page: https://github.com/k-florek/dryad
Author: Kelsey Florek
Author-email: kelsey.florek@slh.wisc.edu
License: UNKNOWN
Platform: UNKNOWN
Classifier: Programming Language :: Python :: 3
Classifier: License :: OSI Approved :: GNU General Public License v3 (GPLv3)
Classifier: Operating System :: OS Independent
Requires-Python: >=3.6
Requires-Dist: pexpect (>=4.8)
